{
    "issue_url": "https://www.aeaweb.org/issues/665",
    "publication_date": "February 2022",
    "article": [
        {
            "url": "https://www.aeaweb.org/articles?id=10.1257/mic.14.1.i",
            "icpsr": null
        },
        {
            "url": "https://www.aeaweb.org/articles?id=10.1257/mic.20190133",
            "icpsr": null
        },
        {
            "url": "https://www.aeaweb.org/articles?id=10.1257/mic.20190125",
            "icpsr": null
        },
        {
            "url": "https://www.aeaweb.org/articles?id=10.1257/mic.20180260",
            "icpsr": "https://doi.org/10.3886/E130441V1"
        },
        {
            "url": "https://www.aeaweb.org/articles?id=10.1257/mic.20190013",
            "icpsr": "https://doi.org/10.3886/E130401V1"
        },
        {
            "url": "https://www.aeaweb.org/articles?id=10.1257/mic.20190153",
            "icpsr": "https://doi.org/10.3886/E119324V2"
        },
        {
            "url": "https://www.aeaweb.org/articles?id=10.1257/mic.20180386",
            "icpsr": "https://doi.org/10.3886/E122101V1"
        },
        {
            "url": "https://www.aeaweb.org/articles?id=10.1257/mic.20190295",
            "icpsr": null
        },
        {
            "url": "https://www.aeaweb.org/articles?id=10.1257/mic.20190089",
            "icpsr": null
        },
        {
            "url": "https://www.aeaweb.org/articles?id=10.1257/mic.20190187",
            "icpsr": null
        },
        {
            "url": "https://www.aeaweb.org/articles?id=10.1257/mic.20190203",
            "icpsr": null
        },
        {
            "url": "https://www.aeaweb.org/articles?id=10.1257/mic.20190166",
            "icpsr": "https://doi.org/10.3886/E119824V1"
        },
        {
            "url": "https://www.aeaweb.org/articles?id=10.1257/mic.20190117",
            "icpsr": "https://doi.org/10.3886/E119694V1"
        },
        {
            "url": "https://www.aeaweb.org/articles?id=10.1257/mic.20190085",
            "icpsr": "https://doi.org/10.3886/E119564V3"
        },
        {
            "url": "https://www.aeaweb.org/articles?id=10.1257/mic.20180044",
            "icpsr": "https://doi.org/10.3886/E127161V1"
        },
        {
            "url": "https://www.aeaweb.org/articles?id=10.1257/mic.20180313",
            "icpsr": null
        },
        {
            "url": "https://www.aeaweb.org/articles?id=10.1257/mic.20190234",
            "icpsr": null
        }
    ]
}