<?xml version="1.0" encoding="UTF-8" standalone="yes"?>
<oaipmHtype xmlns="http://www.openarchives.org/OAI/2.0/" xmlnsterms="http://purl.org/dc/terms/" xmlns="http://www.openarchives.org/OAI/2.0/oai_dc/" xmlns="http://purl.org/dc/elements/1.1/">
    <responseDate>2021-04-14T10:03:03</responseDate>
    <request verb="GetRecord" set="https://www.icpsr.umich.edu/icpsrweb/ICPSR/oai/studies"/>
    <GetRecord>
        <record>
            <header>
                <identifier>113739</identifier>
                <datestamp>Wed Apr 14 10:03:03 EDT 2021</datestamp>
            </header>
            <metadata>
                <dc:oaiDcType>
                    <dc:title>Replication data for: The Effect of Bans and Taxes on Passive Smoking</dc:title>
                    <dc:creator>Jérôme Adda</dc:creator>
                    <dc:creator>Francesca Cornaglia</dc:creator>
                    <dc:identifier>113739</dc:identifier>
                    <dc:identifier>https://doi.org/10.3886/E113739V1</dc:identifier>
                    <dc:description>We evaluate the effect of smoking bans and excise taxes on the exposure
to tobacco smoke of nonsmokers, and we show their unintended
consequences on children. Smoking bans perversely increase nonsmokers'
exposure by displacing smokers to private places where
they contaminate nonsmokers. We exploit data on bio-samples of
cotinine, time use, and smoking cessation, as well as state and time
variation in anti-smoking policies across US states. We find that
higher taxes are an efficient way to decrease exposure to tobacco
smoke. (JEL D12, H25, I12, I18, J13)</dc:description>
                    <dc:subject>D12 Consumer Economics: Empirical Analysis</dc:subject>
                    <dc:subject>H25 Business Taxes and Subsidies including sales and value-added (VAT)</dc:subject>
                    <dc:subject>I12 Health Behavior</dc:subject>
                    <dc:subject>I18 Health: Government Policy; Regulation; Public Health</dc:subject>
                    <dc:subject>J13 Fertility; Family Planning; Child Care; Children; Youth</dc:subject>
                </dc:oaiDcType>
            </metadata>
        </record>
    </GetRecord>
</oaipmHtype>
